cribbage_scorer/__init__.py
cribbage_scorer/cribbage_scorer.py
cribbage_scorer-0.2.5.dist-info/METADATA
cribbage_scorer-0.2.5.dist-info/WHEEL
cribbage_scorer-0.2.5.dist-info/top_level.txt
cribbage_scorer-0.2.5.dist-info/RECORD
