Metadata-Version: 2.1
Name: cribbage-scorer
Version: 0.2.5
Summary: A Cribbage scoring tool
Home-page: https://github.com/phoughton/cribbage_scorer
Author: Peter Houghton
Author-email: pete@investigatingsoftware.co.uk
Classifier: Programming Language :: Python :: 3
Classifier: License :: OSI Approved :: MIT License
Classifier: Operating System :: OS Independent
Requires-Python: >=3.6
Requires-Dist: more-itertools
